{
  "generatedAt": "2026-06-29T18:20:27+00:00",
  "sourcePolicy": "voxel-fit-only",
  "sources": [
    {
      "name": "Freelancer (marketplaces de projets)",
      "url": "https://www.freelancer.com",
      "status": "active",
      "searchedTerms": 0
    }
  ],
  "queryTerms": [],
  "total": 27,
  "countryCount": 0,
  "countries": [],
  "segments": [
    "animation"
  ],
  "errors": [],
  "items": [
    {
      "id": "freelancer:40548536",
      "title": "Realistic Astronaut Ad Animation",
      "sourceUrl": "https://www.freelancer.com/projects/rendering/Realistic-Astronaut-Animation",
      "source": "marketplace:freelancer",
      "country": "Remote",
      "noticeType": "Projet freelance",
      "deadline": "",
      "priority": 98,
      "subject": "product_ad_motion",
      "primarySegment": "animation",
      "segments": [
        "animation"
      ],
      "fitReasons": [
        "Création d'une vidéo publicitaire 3D réaliste"
      ],
      "buyer": "freelancer",
      "archiveMatches": [
        {
          "capability": "product_ad_motion",
          "label": "product_ad_motion"
        }
      ]
    },
    {
      "id": "freelancer:40548575",
      "title": "Professional Landing Page Video Editing",
      "sourceUrl": "https://www.freelancer.com/projects/motion-graphics/Professional-Landing-Page-Video-Editing",
      "source": "marketplace:freelancer",
      "country": "Remote",
      "noticeType": "Projet freelance",
      "deadline": "",
      "priority": 97,
      "subject": "product_ad_motion",
      "primarySegment": "animation",
      "segments": [
        "animation"
      ],
      "fitReasons": [
        "Montage vidéo avec motion graphics, captions, branding, livrable final."
      ],
      "buyer": "freelancer",
      "archiveMatches": [
        {
          "capability": "product_ad_motion",
          "label": "product_ad_motion"
        }
      ]
    },
    {
      "id": "freelancer:40548533",
      "title": "Chess Learning Video Animation for REKI Chess",
      "sourceUrl": "https://www.freelancer.com/projects/2d-animation/Chess-Learning-Video-Animation-for",
      "source": "marketplace:freelancer",
      "country": "Remote",
      "noticeType": "Projet freelance",
      "deadline": "",
      "priority": 97,
      "subject": "product_ad_motion",
      "primarySegment": "animation",
      "segments": [
        "animation"
      ],
      "fitReasons": [
        "Création de vidéos motion‑graphics éducatives 2D"
      ],
      "buyer": "freelancer",
      "archiveMatches": [
        {
          "capability": "product_ad_motion",
          "label": "product_ad_motion"
        }
      ]
    },
    {
      "id": "freelancer:40548456",
      "title": "3D Fantasy Animation",
      "sourceUrl": "https://www.freelancer.com/projects/blender/Fantasy-Animation",
      "source": "marketplace:freelancer",
      "country": "Remote",
      "noticeType": "Projet freelance",
      "deadline": "",
      "priority": 97,
      "subject": "character_animation",
      "primarySegment": "animation",
      "segments": [
        "animation"
      ],
      "fitReasons": [
        "Création d'animation 3D de personnages fantasy éducative"
      ],
      "buyer": "freelancer",
      "archiveMatches": [
        {
          "capability": "character_animation",
          "label": "character_animation"
        }
      ]
    },
    {
      "id": "freelancer:40548237",
      "title": "4-Screen Minimalist Kebab Menu",
      "sourceUrl": "https://www.freelancer.com/projects/2d-animation/Screen-Minimalist-Kebab-Menu",
      "source": "marketplace:freelancer",
      "country": "Remote",
      "noticeType": "Projet freelance",
      "deadline": "",
      "priority": 97,
      "subject": "product_ad_motion",
      "primarySegment": "animation",
      "segments": [
        "animation"
      ],
      "fitReasons": [
        "Animation minimaliste pour affichage digital sur quatre écrans"
      ],
      "buyer": "freelancer",
      "archiveMatches": [
        {
          "capability": "product_ad_motion",
          "label": "product_ad_motion"
        }
      ]
    },
    {
      "id": "freelancer:40548152",
      "title": "First-Person Action Game Development",
      "sourceUrl": "https://www.freelancer.com/projects/3d-animation/First-Person-Action-Game-Development",
      "source": "marketplace:freelancer",
      "country": "Remote",
      "noticeType": "Projet freelance",
      "deadline": "",
      "priority": 97,
      "subject": "product_ad_motion",
      "primarySegment": "animation",
      "segments": [
        "animation"
      ],
      "fitReasons": [
        "Création d'animation 3D de pack-opening premium"
      ],
      "buyer": "freelancer",
      "archiveMatches": [
        {
          "capability": "product_ad_motion",
          "label": "product_ad_motion"
        }
      ]
    },
    {
      "id": "freelancer:40548053",
      "title": "Fintech App Logo Animation",
      "sourceUrl": "https://www.freelancer.com/projects/logo-animation/Fintech-App-Logo-Animation",
      "source": "marketplace:freelancer",
      "country": "Remote",
      "noticeType": "Projet freelance",
      "deadline": "",
      "priority": 97,
      "subject": "product_ad_motion",
      "primarySegment": "animation",
      "segments": [
        "animation"
      ],
      "fitReasons": [
        "Création d'animation logo mobile, motion graphics produit"
      ],
      "buyer": "freelancer",
      "archiveMatches": [
        {
          "capability": "product_ad_motion",
          "label": "product_ad_motion"
        }
      ]
    },
    {
      "id": "freelancer:40547651",
      "title": "Podcast Intro & Outro Transitions",
      "sourceUrl": "https://www.freelancer.com/projects/video-production/Podcast-Intro-Outro-Transitions",
      "source": "marketplace:freelancer",
      "country": "Remote",
      "noticeType": "Projet freelance",
      "deadline": "",
      "priority": 97,
      "subject": "product_ad_motion",
      "primarySegment": "animation",
      "segments": [
        "animation"
      ],
      "fitReasons": [
        "Création d'animations d'intro/outro podcast en motion graphics"
      ],
      "buyer": "freelancer",
      "archiveMatches": [
        {
          "capability": "product_ad_motion",
          "label": "product_ad_motion"
        }
      ]
    },
    {
      "id": "freelancer:40547566",
      "title": "Vertical Parking 3D Animation",
      "sourceUrl": "https://www.freelancer.com/projects/3d-design/Vertical-Parking-Animation",
      "source": "marketplace:freelancer",
      "country": "Remote",
      "noticeType": "Projet freelance",
      "deadline": "",
      "priority": 97,
      "subject": "product_ad_motion",
      "primarySegment": "animation",
      "segments": [
        "animation"
      ],
      "fitReasons": [
        "Animation 3D produit technique, demande de rendu vidéo"
      ],
      "buyer": "freelancer",
      "archiveMatches": [
        {
          "capability": "product_ad_motion",
          "label": "product_ad_motion"
        }
      ]
    },
    {
      "id": "freelancer:40548330",
      "title": "Rigged Chameleon Mascot Model",
      "sourceUrl": "https://www.freelancer.com/projects/blender/Rigged-Chameleon-Mascot-Model",
      "source": "marketplace:freelancer",
      "country": "Remote",
      "noticeType": "Projet freelance",
      "deadline": "",
      "priority": 97,
      "subject": "character_animation",
      "primarySegment": "animation",
      "segments": [
        "animation"
      ],
      "fitReasons": [
        "Création, texturage et rigging de mascotte 3D"
      ],
      "buyer": "freelancer",
      "archiveMatches": [
        {
          "capability": "character_animation",
          "label": "character_animation"
        }
      ]
    },
    {
      "id": "freelancer:40548198",
      "title": "26-Min Motion Graphics YouTube Video Editing | Budget ₹1,500 | Only Bid If You Accept",
      "sourceUrl": "https://www.freelancer.com/projects/motion-graphics/Min-Motion-Graphics-YouTube-Video",
      "source": "marketplace:freelancer",
      "country": "Remote",
      "noticeType": "Projet freelance",
      "deadline": "",
      "priority": 97,
      "subject": "product_ad_motion",
      "primarySegment": "animation",
      "segments": [
        "animation"
      ],
      "fitReasons": [
        "Demande de montage vidéo avec motion graphics, service créatif"
      ],
      "buyer": "freelancer",
      "archiveMatches": [
        {
          "capability": "product_ad_motion",
          "label": "product_ad_motion"
        }
      ]
    },
    {
      "id": "freelancer:40547911",
      "title": "Mixed Media Company Video",
      "sourceUrl": "https://www.freelancer.com/projects/motion-graphics/Mixed-Media-Company-Video",
      "source": "marketplace:freelancer",
      "country": "Remote",
      "noticeType": "Projet freelance",
      "deadline": "",
      "priority": 97,
      "subject": "product_ad_motion",
      "primarySegment": "animation",
      "segments": [
        "animation"
      ],
      "fitReasons": [
        "Demande de création vidéo mixte corporate, animation et live‑action"
      ],
      "buyer": "freelancer",
      "archiveMatches": [
        {
          "capability": "product_ad_motion",
          "label": "product_ad_motion"
        }
      ]
    },
    {
      "id": "freelancer:40547367",
      "title": "Land and Aquatic exercises animation 2026 -- 3",
      "sourceUrl": "https://www.freelancer.com/projects/animation/Land-Aquatic-exercises-animation-40547367",
      "source": "marketplace:freelancer",
      "country": "Remote",
      "noticeType": "Projet freelance",
      "deadline": "",
      "priority": 97,
      "subject": "character_animation",
      "primarySegment": "animation",
      "segments": [
        "animation"
      ],
      "fitReasons": [
        "Création d'animations de personnages semi-réalistes"
      ],
      "buyer": "freelancer",
      "archiveMatches": [
        {
          "capability": "character_animation",
          "label": "character_animation"
        }
      ]
    },
    {
      "id": "freelancer:40547336",
      "title": "Professional HD Video & Lyric Upgrade",
      "sourceUrl": "https://www.freelancer.com/projects/audio-editing/Professional-Video-Lyric-Upgrade",
      "source": "marketplace:freelancer",
      "country": "Remote",
      "noticeType": "Projet freelance",
      "deadline": "",
      "priority": 97,
      "subject": "product_ad_motion",
      "primarySegment": "animation",
      "segments": [
        "animation"
      ],
      "fitReasons": [
        "Post‑production vidéo avec motion graphics et sous‑titres"
      ],
      "buyer": "freelancer",
      "archiveMatches": [
        {
          "capability": "product_ad_motion",
          "label": "product_ad_motion"
        }
      ]
    },
    {
      "id": "freelancer:40547187",
      "title": "3D Kids Cartoon Animator Needed",
      "sourceUrl": "https://www.freelancer.com/projects/character-design/Kids-Cartoon-Animator-Needed",
      "source": "marketplace:freelancer",
      "country": "Remote",
      "noticeType": "Projet freelance",
      "deadline": "",
      "priority": 97,
      "subject": "character_animation",
      "primarySegment": "animation",
      "segments": [
        "animation"
      ],
      "fitReasons": [
        "Création complète d'animations 3D de personnages pour vidéos éducatives."
      ],
      "buyer": "freelancer",
      "archiveMatches": [
        {
          "capability": "character_animation",
          "label": "character_animation"
        }
      ]
    },
    {
      "id": "freelancer:40547068",
      "title": "3D AI Animation Branding",
      "sourceUrl": "https://www.freelancer.com/projects/ai-animation/Animation-Branding",
      "source": "marketplace:freelancer",
      "country": "Remote",
      "noticeType": "Projet freelance",
      "deadline": "",
      "priority": 97,
      "subject": "product_ad_motion",
      "primarySegment": "animation",
      "segments": [
        "animation"
      ],
      "fitReasons": [
        "Création d'animation 3D publicitaire conforme au catalogue"
      ],
      "buyer": "freelancer",
      "archiveMatches": [
        {
          "capability": "product_ad_motion",
          "label": "product_ad_motion"
        }
      ]
    },
    {
      "id": "freelancer:40547065",
      "title": "Abstract 3D Brand Intro Video",
      "sourceUrl": "https://www.freelancer.com/projects/motion-graphics/Abstract-Brand-Intro-Video",
      "source": "marketplace:freelancer",
      "country": "Remote",
      "noticeType": "Projet freelance",
      "deadline": "",
      "priority": 97,
      "subject": "product_ad_motion",
      "primarySegment": "animation",
      "segments": [
        "animation"
      ],
      "fitReasons": [
        "Création d'une vidéo 3D motion‑graphics brand intro"
      ],
      "buyer": "freelancer",
      "archiveMatches": [
        {
          "capability": "product_ad_motion",
          "label": "product_ad_motion"
        }
      ]
    },
    {
      "id": "freelancer:40547061",
      "title": "3D AI Marketing Animation ",
      "sourceUrl": "https://www.freelancer.com/projects/ai-animation/Marketing-Animation",
      "source": "marketplace:freelancer",
      "country": "Remote",
      "noticeType": "Projet freelance",
      "deadline": "",
      "priority": 97,
      "subject": "product_ad_motion",
      "primarySegment": "animation",
      "segments": [
        "animation"
      ],
      "fitReasons": [
        "Création d'animation 3D marketing pour produit AI"
      ],
      "buyer": "freelancer",
      "archiveMatches": [
        {
          "capability": "product_ad_motion",
          "label": "product_ad_motion"
        }
      ]
    },
    {
      "id": "freelancer:40547013",
      "title": "Solana Bidding Teaser Video",
      "sourceUrl": "https://www.freelancer.com/projects/video-production/Solana-Bidding-Teaser-Video",
      "source": "marketplace:freelancer",
      "country": "Remote",
      "noticeType": "Projet freelance",
      "deadline": "",
      "priority": 97,
      "subject": "product_ad_motion",
      "primarySegment": "animation",
      "segments": [
        "animation"
      ],
      "fitReasons": [
        "Création d'une vidéo teaser motion‑graphics publicitaire"
      ],
      "buyer": "freelancer",
      "archiveMatches": [
        {
          "capability": "product_ad_motion",
          "label": "product_ad_motion"
        }
      ]
    },
    {
      "id": "freelancer:40546833",
      "title": "AI Brand Awareness Video",
      "sourceUrl": "https://www.freelancer.com/projects/after-effects/Brand-Awareness-Video",
      "source": "marketplace:freelancer",
      "country": "Remote",
      "noticeType": "Projet freelance",
      "deadline": "",
      "priority": 97,
      "subject": "product_ad_motion",
      "primarySegment": "animation",
      "segments": [
        "animation"
      ],
      "fitReasons": [
        "Création vidéo brand, motion graphics, post‑production"
      ],
      "buyer": "freelancer",
      "archiveMatches": [
        {
          "capability": "product_ad_motion",
          "label": "product_ad_motion"
        }
      ]
    },
    {
      "id": "freelancer:40546752",
      "title": "Clinic SaaS Lead-Gen Video",
      "sourceUrl": "https://www.freelancer.com/projects/motion-graphics/Clinic-SaaS-Lead-Gen-Video",
      "source": "marketplace:freelancer",
      "country": "Remote",
      "noticeType": "Projet freelance",
      "deadline": "",
      "priority": 97,
      "subject": "product_ad_motion",
      "primarySegment": "animation",
      "segments": [
        "animation"
      ],
      "fitReasons": [
        "Création d'une vidéo publicitaire motion graphics pour SaaS."
      ],
      "buyer": "freelancer",
      "archiveMatches": [
        {
          "capability": "product_ad_motion",
          "label": "product_ad_motion"
        }
      ]
    },
    {
      "id": "freelancer:40512541",
      "title": "3D Puppet Animation Series",
      "sourceUrl": "https://www.freelancer.com/projects/ai-animation/Puppet-Animation-Series",
      "source": "marketplace:freelancer",
      "country": "Remote",
      "noticeType": "Projet freelance",
      "deadline": "",
      "priority": 97,
      "subject": "character_animation",
      "primarySegment": "animation",
      "segments": [
        "animation"
      ],
      "fitReasons": [
        "Création d'animations 3D de personnages puppets pour série enfantine"
      ],
      "buyer": "freelancer",
      "archiveMatches": [
        {
          "capability": "character_animation",
          "label": "character_animation"
        }
      ]
    },
    {
      "id": "freelancer:40546409",
      "title": "Cinematic 8K Animation of Premium Paint Brush",
      "sourceUrl": "https://www.freelancer.com/projects/3d-animation/Cinematic-Animation-Premium-Paint-Brush",
      "source": "marketplace:freelancer",
      "country": "Remote",
      "noticeType": "Projet freelance",
      "deadline": "",
      "priority": 97,
      "subject": "product_ad_motion",
      "primarySegment": "animation",
      "segments": [
        "animation"
      ],
      "fitReasons": [
        "Création d'animation produit publicitaire ultra‑réaliste en 8K"
      ],
      "buyer": "freelancer",
      "archiveMatches": [
        {
          "capability": "product_ad_motion",
          "label": "product_ad_motion"
        }
      ]
    },
    {
      "id": "freelancer:40548317",
      "title": "Inspiring AI Promo Video for Welfare Center",
      "sourceUrl": "https://www.freelancer.com/projects/3d-animation/Inspiring-Promo-Video-for-Welfare",
      "source": "marketplace:freelancer",
      "country": "Remote",
      "noticeType": "Projet freelance",
      "deadline": "",
      "priority": 96,
      "subject": "product_ad_motion",
      "primarySegment": "animation",
      "segments": [
        "animation"
      ],
      "fitReasons": [
        "Création d'une vidéo promotionnelle cinématographique humanitaire"
      ],
      "buyer": "freelancer",
      "archiveMatches": [
        {
          "capability": "product_ad_motion",
          "label": "product_ad_motion"
        }
      ]
    },
    {
      "id": "freelancer:40547987",
      "title": "AI-Powered Promotional Video Editing",
      "sourceUrl": "https://www.freelancer.com/projects/2d-animation/Powered-Promotional-Video-Editing",
      "source": "marketplace:freelancer",
      "country": "Remote",
      "noticeType": "Projet freelance",
      "deadline": "",
      "priority": 96,
      "subject": "product_ad_motion",
      "primarySegment": "animation",
      "segments": [
        "animation"
      ],
      "fitReasons": [
        "Création vidéo promotionnelle avec motion graphics 2D/3D"
      ],
      "buyer": "freelancer",
      "archiveMatches": [
        {
          "capability": "product_ad_motion",
          "label": "product_ad_motion"
        }
      ]
    },
    {
      "id": "freelancer:40547694",
      "title": "Dynamic Animations For Mobile Game",
      "sourceUrl": "https://www.freelancer.com/projects/unity/Dynamic-Animations-For-Mobile-Game",
      "source": "marketplace:freelancer",
      "country": "Remote",
      "noticeType": "Projet freelance",
      "deadline": "",
      "priority": 96,
      "subject": "product_ad_motion",
      "primarySegment": "animation",
      "segments": [
        "animation"
      ],
      "fitReasons": [
        "Création d'animations et effets visuels pour jeu mobile, service créatif."
      ],
      "buyer": "freelancer",
      "archiveMatches": [
        {
          "capability": "product_ad_motion",
          "label": "product_ad_motion"
        }
      ]
    },
    {
      "id": "freelancer:40546326",
      "title": "Gacha-Style 3D Character Artist Needed",
      "sourceUrl": "https://www.freelancer.com/projects/3d-rigging/Gacha-Style-Character-Artist-Needed",
      "source": "marketplace:freelancer",
      "country": "Remote",
      "noticeType": "Projet freelance",
      "deadline": "",
      "priority": 96,
      "subject": "character_animation",
      "primarySegment": "animation",
      "segments": [
        "animation"
      ],
      "fitReasons": [
        "Création, rigging, animation et VFX de personnages 3D stylisés"
      ],
      "buyer": "freelancer",
      "archiveMatches": [
        {
          "capability": "character_animation",
          "label": "character_animation"
        }
      ]
    }
  ]
}
